{
  "id": "nie-ma-nic",
  "title": "Nie ma nic",
  "category": {
    "id": "common",
    "name": "Obozowe"
  },
  "created": {
    "name": "spiewnik-mmakos",
    "time": 1727355582,
    "userVerified": true,
    "verified": false
  },
  "verses": [
    {
      "lines": [
        {
          "text": [
            {
              "text": "Nie rozglądaj się, bo wokół nie ma nic"
            }
          ],
          "chords": {
            "chords": [
              {
                "chords": [
                  {
                    "chord": {
                      "note": {
                        "base": "E"
                      },
                      "minor": true
                    }
                  },
                  {
                    "chord": {
                      "note": {
                        "base": "C"
                      }
                    }
                  },
                  {
                    "chord": {
                      "note": {
                        "base": "G"
                      }
                    }
                  },
                  {
                    "chord": {
                      "note": {
                        "base": "D"
                      }
                    }
                  }
                ]
              }
            ]
          }
        },
        {
          "text": [
            {
              "text": "Za oknami wszystko znikło - nie ma nic"
            }
          ],
          "chords": {
            "chords": [
              {
                "chords": [
                  {
                    "chord": {
                      "note": {
                        "base": "E"
                      },
                      "minor": true
                    }
                  },
                  {
                    "chord": {
                      "note": {
                        "base": "C"
                      }
                    }
                  },
                  {
                    "chord": {
                      "note": {
                        "base": "G"
                      }
                    }
                  },
                  {
                    "chord": {
                      "note": {
                        "base": "D"
                      }
                    }
                  }
                ]
              }
            ]
          }
        },
        {
          "text": [
            {
              "text": "Nie ma sekund, nie ma godzin, nie ma lat"
            }
          ],
          "chords": {
            "chords": [
              {
                "chords": [
                  {
                    "chord": {
                      "note": {
                        "base": "E"
                      },
                      "minor": true
                    }
                  },
                  {
                    "chord": {
                      "note": {
                        "base": "C"
                      }
                    }
                  },
                  {
                    "chord": {
                      "note": {
                        "base": "G"
                      }
                    }
                  },
                  {
                    "chord": {
                      "note": {
                        "base": "D"
                      }
                    }
                  }
                ]
              }
            ]
          }
        },
        {
          "text": [
            {
              "text": "Jakby ktoś wyłączył z prądu cały świat"
            }
          ],
          "chords": {
            "chords": [
              {
                "chords": [
                  {
                    "chord": {
                      "note": {
                        "base": "E"
                      },
                      "minor": true
                    }
                  },
                  {
                    "chord": {
                      "note": {
                        "base": "C"
                      }
                    }
                  },
                  {
                    "chord": {
                      "note": {
                        "base": "G"
                      }
                    }
                  },
                  {
                    "chord": {
                      "note": {
                        "base": "D"
                      }
                    }
                  }
                ]
              }
            ]
          }
        }
      ],
      "indent": 0
    },
    {
      "lines": [
        {
          "text": [
            {
              "text": "Telefony głuche milczą, nie ma nic"
            }
          ],
          "chords": {
            "chords": [
              {
                "chords": [
                  {
                    "chord": {
                      "note": {
                        "base": "E"
                      },
                      "minor": true
                    }
                  },
                  {
                    "chord": {
                      "note": {
                        "base": "C"
                      }
                    }
                  },
                  {
                    "chord": {
                      "note": {
                        "base": "G"
                      }
                    }
                  },
                  {
                    "chord": {
                      "note": {
                        "base": "D"
                      }
                    }
                  }
                ]
              }
            ]
          }
        },
        {
          "text": [
            {
              "text": "Z myśli co przemknęła nagle - nie ma nic"
            }
          ],
          "chords": {
            "chords": [
              {
                "chords": [
                  {
                    "chord": {
                      "note": {
                        "base": "E"
                      },
                      "minor": true
                    }
                  },
                  {
                    "chord": {
                      "note": {
                        "base": "C"
                      }
                    }
                  },
                  {
                    "chord": {
                      "note": {
                        "base": "G"
                      }
                    }
                  },
                  {
                    "chord": {
                      "note": {
                        "base": "D"
                      }
                    }
                  }
                ]
              }
            ]
          }
        },
        {
          "text": [
            {
              "text": "Nawet burza poszła w diabły przespać gniew"
            }
          ],
          "chords": {
            "chords": [
              {
                "chords": [
                  {
                    "chord": {
                      "note": {
                        "base": "E"
                      },
                      "minor": true
                    }
                  },
                  {
                    "chord": {
                      "note": {
                        "base": "C"
                      }
                    }
                  },
                  {
                    "chord": {
                      "note": {
                        "base": "G"
                      }
                    }
                  },
                  {
                    "chord": {
                      "note": {
                        "base": "D"
                      }
                    }
                  }
                ]
              }
            ]
          }
        },
        {
          "text": [
            {
              "text": "Tylko serce w swoim rytmie tłoczy krew"
            }
          ],
          "chords": {
            "chords": [
              {
                "chords": [
                  {
                    "chord": {
                      "note": {
                        "base": "E"
                      },
                      "minor": true
                    }
                  },
                  {
                    "chord": {
                      "note": {
                        "base": "C"
                      }
                    }
                  },
                  {
                    "chord": {
                      "note": {
                        "base": "G"
                      }
                    }
                  },
                  {
                    "chord": {
                      "note": {
                        "base": "D"
                      }
                    }
                  }
                ]
              }
            ]
          }
        }
      ],
      "indent": 0
    },
    {
      "lines": [
        {
          "text": [
            {
              "text": "Nie ma nic oprócz nas z wolna sączy się czas"
            }
          ],
          "chords": {
            "chords": [
              {
                "chords": [
                  {
                    "chord": {
                      "note": {
                        "base": "E"
                      },
                      "minor": true
                    }
                  },
                  {
                    "chord": {
                      "note": {
                        "base": "H"
                      },
                      "minor": true,
                      "base": {
                        "elements": [
                          {
                            "interval": 3
                          }
                        ]
                      }
                    },
                    "alternative": {
                      "note": {
                        "base": "E"
                      },
                      "minor": true
                    }
                  }
                ]
              }
            ]
          }
        },
        {
          "text": [
            {
              "text": "Odpływamy powoli w inny świat"
            }
          ],
          "chords": {
            "chords": [
              {
                "chords": [
                  {
                    "chord": {
                      "note": {
                        "base": "G"
                      }
                    }
                  },
                  {
                    "chord": {
                      "note": {
                        "base": "D"
                      }
                    }
                  },
                  {
                    "chord": {
                      "note": {
                        "base": "G"
                      }
                    }
                  },
                  {
                    "chord": {
                      "note": {
                        "base": "H"
                      }
                    }
                  }
                ]
              }
            ]
          }
        },
        {
          "text": [
            {
              "text": "Nie ma nic tylko my nasze plany i sny"
            }
          ],
          "chords": {
            "chords": [
              {
                "chords": [
                  {
                    "chord": {
                      "note": {
                        "base": "E"
                      },
                      "minor": true
                    }
                  },
                  {
                    "chord": {
                      "note": {
                        "base": "H"
                      },
                      "minor": true,
                      "base": {
                        "elements": [
                          {
                            "interval": 3
                          }
                        ]
                      }
                    },
                    "alternative": {
                      "note": {
                        "base": "E"
                      },
                      "minor": true
                    }
                  }
                ]
              }
            ]
          }
        },
        {
          "text": [
            {
              "text": "W naszym niebie na ziemi tylko my"
            }
          ],
          "chords": {
            "chords": [
              {
                "chords": [
                  {
                    "chord": {
                      "note": {
                        "base": "G"
                      }
                    }
                  },
                  {
                    "chord": {
                      "note": {
                        "base": "D"
                      }
                    }
                  },
                  {
                    "chord": {
                      "note": {
                        "base": "G"
                      }
                    }
                  },
                  {
                    "chord": {
                      "note": {
                        "base": "H"
                      }
                    }
                  }
                ]
              }
            ]
          }
        }
      ],
      "indent": 1
    },
    {
      "lines": [
        {
          "text": [
            {
              "text": "Czasem trzeba z życia zniknąć, żeby żyć"
            }
          ],
          "chords": {
            "chords": [
              {
                "chords": [
                  {
                    "chord": {
                      "note": {
                        "base": "E"
                      },
                      "minor": true
                    }
                  },
                  {
                    "chord": {
                      "note": {
                        "base": "C"
                      }
                    }
                  },
                  {
                    "chord": {
                      "note": {
                        "base": "G"
                      }
                    }
                  },
                  {
                    "chord": {
                      "note": {
                        "base": "D"
                      }
                    }
                  }
                ]
              }
            ]
          }
        },
        {
          "text": [
            {
              "text": "Czasem siebie w głąb przeniknąć, żeby żyć"
            }
          ],
          "chords": {
            "chords": [
              {
                "chords": [
                  {
                    "chord": {
                      "note": {
                        "base": "E"
                      },
                      "minor": true
                    }
                  },
                  {
                    "chord": {
                      "note": {
                        "base": "C"
                      }
                    }
                  },
                  {
                    "chord": {
                      "note": {
                        "base": "G"
                      }
                    }
                  },
                  {
                    "chord": {
                      "note": {
                        "base": "D"
                      }
                    }
                  }
                ]
              }
            ]
          }
        },
        {
          "text": [
            {
              "text": "By na nowo umieć dostrzec co się ma"
            }
          ],
          "chords": {
            "chords": [
              {
                "chords": [
                  {
                    "chord": {
                      "note": {
                        "base": "E"
                      },
                      "minor": true
                    }
                  },
                  {
                    "chord": {
                      "note": {
                        "base": "C"
                      }
                    }
                  },
                  {
                    "chord": {
                      "note": {
                        "base": "G"
                      }
                    }
                  },
                  {
                    "chord": {
                      "note": {
                        "base": "D"
                      }
                    }
                  }
                ]
              }
            ]
          }
        },
        {
          "text": [
            {
              "text": "Życie przecież taką krótką chwilę trwa"
            }
          ],
          "chords": {
            "chords": [
              {
                "chords": [
                  {
                    "chord": {
                      "note": {
                        "base": "E"
                      },
                      "minor": true
                    }
                  },
                  {
                    "chord": {
                      "note": {
                        "base": "C"
                      }
                    }
                  },
                  {
                    "chord": {
                      "note": {
                        "base": "G"
                      }
                    }
                  },
                  {
                    "chord": {
                      "note": {
                        "base": "D"
                      }
                    }
                  }
                ]
              }
            ]
          }
        }
      ],
      "indent": 0
    },
    {
      "lines": [
        {
          "text": [
            {
              "text": "Nie ma nic…"
            }
          ]
        }
      ],
      "indent": 1,
      "verseRef": 2
    }
  ],
  "key": {
    "songbook": {
      "note": {
        "base": "E"
      },
      "minor": true
    }
  },
  "performers": [
    {
      "name": "Golec",
      "lastName": "uOrkiestra"
    }
  ],
  "next": {
    "id": "nie-placz-ewka",
    "title": "Nie płacz Ewka"
  },
  "previous": {
    "id": "nie-daj-mi-odejsc",
    "title": "Nie daj mi odejść"
  }
}